dash_aladin_lite/DashAladinLite.py
dash_aladin_lite/__init__.py
dash_aladin_lite/_imports_.py
dash_aladin_lite/dash_aladin_lite.min.js
dash_aladin_lite/dash_aladin_lite.min.js.map
dash_aladin_lite/metadata.json
dash_aladin_lite/package-info.json
dash_aladin_lite/third_party/aladin.min.css
dash_aladin_lite/third_party/aladin.min.js
dash_aladin_lite/third_party/jquery-1.10.1.min.js
dash_aladin_lite-0.1.1.dist-info/LICENSE
dash_aladin_lite-0.1.1.dist-info/METADATA
dash_aladin_lite-0.1.1.dist-info/WHEEL
dash_aladin_lite-0.1.1.dist-info/top_level.txt
dash_aladin_lite-0.1.1.dist-info/RECORD
