Metadata-Version: 2.1
Name: dash-aladin-lite
Version: 0.1.1
Summary: Dash component for Aladin Lite.
Home-page: https://github.com/toltec-astro/dash_aladin_lite
Author: Zhiyuan Ma <zhiyuanma@umass.edu>
License: BSD
Project-URL: Bug Reports, https://github.com/toltec-astro/dash_aladin_lite/issues
Project-URL: Source, https://github.com/toltec-astro/dash_aladin_lite
Platform: UNKNOWN
Classifier: Framework :: Dash
Classifier: License :: OSI Approved :: BSD License
Classifier: Programming Language :: Python :: 3
Classifier: Programming Language :: Python :: 3.8
Requires-Dist: dash
